python_pack/__init__.py
python_pack/utils.py
python_pack-0.0.0.dist-info/METADATA
python_pack-0.0.0.dist-info/WHEEL
python_pack-0.0.0.dist-info/top_level.txt
python_pack-0.0.0.dist-info/RECORD
